periodicity_detection/__init__.py
periodicity_detection/__main__.py
periodicity_detection/_version.py
periodicity_detection/py.typed
periodicity_detection/methods/__init__.py
periodicity_detection/methods/autocorrelation.py
periodicity_detection/methods/autoperiod.py
periodicity_detection/methods/fft.py
periodicity_detection/methods/find_length.py
periodicity_detection/methods/findfrequency.py
periodicity_detection/methods/number_peaks.py
periodicity_detection-0.1.3.dist-info/LICENSE
periodicity_detection-0.1.3.dist-info/METADATA
periodicity_detection-0.1.3.dist-info/WHEEL
periodicity_detection-0.1.3.dist-info/entry_points.txt
periodicity_detection-0.1.3.dist-info/top_level.txt
periodicity_detection-0.1.3.dist-info/RECORD
