Metadata-Version: 2.1
Name: periodicity-detection
Version: 0.1.3
Summary: Detect the dominant period in univariate, equidistant time series data.
Home-page: https://github.com/CodeLionX/periodicity_detection
Author: Sebastian Schmidl
Author-email: sebastian.schmidl@hpi.de
License: MIT
Classifier: License :: OSI Approved :: MIT License
Classifier: Programming Language :: Python :: 3
Classifier: Programming Language :: Python :: 3.7
Classifier: Programming Language :: Python :: 3.8
Classifier: Programming Language :: Python :: 3.9
Classifier: Programming Language :: Python :: 3.10
Classifier: Programming Language :: Python :: 3.11
Classifier: Typing :: Typed
Classifier: Topic :: Software Development
Classifier: Topic :: Scientific/Engineering
Classifier: Intended Audience :: Science/Research
Classifier: Intended Audience :: Developers
Requires-Python: >=3.7
License-File: LICENSE
Requires-Dist: numpy >=1.21.6
Requires-Dist: pandas >=1.3.5
Requires-Dist: scipy >=1.7.3
Requires-Dist: statsmodels >=0.13.5
Requires-Dist: typing-extensions >=4.7.1
Requires-Dist: matplotlib >=3.5.3
Requires-Dist: spectrum <0.9,>=0.8.1 ; python_version < "3.8"
Requires-Dist: spectrum >=0.8 ; python_version >= "3.8"
Provides-Extra: dev
Requires-Dist: pytest ; extra == 'dev'
Requires-Dist: pytest-cov ; extra == 'dev'
Requires-Dist: mypy ==0.920 ; extra == 'dev'
Requires-Dist: flake8 ==5.0.4 ; extra == 'dev'
Requires-Dist: black ==23.1 ; extra == 'dev'
Requires-Dist: pre-commit ==2.21 ; extra == 'dev'
Provides-Extra: docs
Requires-Dist: sphinx ==5.0.2 ; extra == 'docs'
Requires-Dist: myst-parser ==0.18.0 ; extra == 'docs'
Requires-Dist: sphinx-rtd-theme ==1.0.0 ; extra == 'docs'
Requires-Dist: sphinx-rtd-dark-mode ==1.2.4 ; extra == 'docs'
